nonebot_plugin_pvz/__init__.py
nonebot_plugin_pvz/config.py
nonebot_plugin_pvz/font/msyh.ttf
nonebot_plugin_pvz/images/pvz/base/buckethead_zombie.png
nonebot_plugin_pvz/images/pvz/base/cabbage_pult.png
nonebot_plugin_pvz/images/pvz/base/chomper.png
nonebot_plugin_pvz/images/pvz/base/conehead_zombie.png
nonebot_plugin_pvz/images/pvz/base/football_zombie.png
nonebot_plugin_pvz/images/pvz/base/fume_shroom.png
nonebot_plugin_pvz/images/pvz/base/gargantuar.png
nonebot_plugin_pvz/images/pvz/base/gatling_pea.png
nonebot_plugin_pvz/images/pvz/base/imp.png
nonebot_plugin_pvz/images/pvz/base/kernet_pult.png
nonebot_plugin_pvz/images/pvz/base/lawn.png
nonebot_plugin_pvz/images/pvz/base/magnet_shroom.png
nonebot_plugin_pvz/images/pvz/base/melon_pult.png
nonebot_plugin_pvz/images/pvz/base/pea_shooter.png
nonebot_plugin_pvz/images/pvz/base/pogo_zombie.png
nonebot_plugin_pvz/images/pvz/base/pole_vaulting_zombie.png
nonebot_plugin_pvz/images/pvz/base/puff_shroom.png
nonebot_plugin_pvz/images/pvz/base/repeater.png
nonebot_plugin_pvz/images/pvz/base/scaredy_shroom.png
nonebot_plugin_pvz/images/pvz/base/screen_door_zombie.png
nonebot_plugin_pvz/images/pvz/base/snow_pea.png
nonebot_plugin_pvz/images/pvz/base/spikerock.png
nonebot_plugin_pvz/images/pvz/base/spikeweed.png
nonebot_plugin_pvz/images/pvz/base/tall_nut.png
nonebot_plugin_pvz/images/pvz/base/torchwood.png
nonebot_plugin_pvz/images/pvz/base/wall_nut.png
nonebot_plugin_pvz/images/pvz/base/winter_melon.png
nonebot_plugin_pvz/images/pvz/base/zombie.png
nonebot_plugin_pvz/images/pvz/base/伽刚特尔.png
nonebot_plugin_pvz/images/pvz/base/冰瓜.png
nonebot_plugin_pvz/images/pvz/base/卷心菜投手.png
nonebot_plugin_pvz/images/pvz/base/双发射手.png
nonebot_plugin_pvz/images/pvz/base/地刺.png
nonebot_plugin_pvz/images/pvz/base/地刺王.png
nonebot_plugin_pvz/images/pvz/base/坚果墙.png
nonebot_plugin_pvz/images/pvz/base/大喷菇.png
nonebot_plugin_pvz/images/pvz/base/寒冰射手.png
nonebot_plugin_pvz/images/pvz/base/小喷菇.png
nonebot_plugin_pvz/images/pvz/base/小鬼僵尸.png
nonebot_plugin_pvz-1.3.9.dist-info/LICENSE
nonebot_plugin_pvz-1.3.9.dist-info/METADATA
nonebot_plugin_pvz-1.3.9.dist-info/WHEEL
nonebot_plugin_pvz-1.3.9.dist-info/top_level.txt
nonebot_plugin_pvz-1.3.9.dist-info/RECORD
