Metadata-Version: 2.1
Name: nonebot-plugin-pvz
Version: 1.3.9
Summary: A plugin of nonebot2, which is support service to play pvz in group chat.
Home-page: http://www.lcgx.space/home
Author: longchengguxiao
Author-email: 1298919732@qq.com
License: AGPL-3.0 License
Platform: all
Classifier: Intended Audience :: Developers
Classifier: Operating System :: OS Independent
Classifier: Natural Language :: Chinese (Simplified)
Classifier: Programming Language :: Python
Classifier: Programming Language :: Python :: 3.8
Classifier: Programming Language :: Python :: 3.9
Classifier: Topic :: Software Development :: Libraries
License-File: LICENSE
Requires-Dist: numpy
Requires-Dist: pillow
Requires-Dist: nonebot2 (>=2.0.0a16)
Requires-Dist: nonebot-adapter-onebot (>=2.0.0b1)
Requires-Dist: nonebot-plugin-apscheduler (>=0.2.0)
